data/__init__.py
data/filters/__init__.py
data/filters/filters.py
lib/__init__.py
lib/error_handling.py
lib/filesystem.py
lib/format_csv.py
lib/json2csv.py
lib/msg_printer.py
tests/__init__.py
tests/flat_test.py
tests/json2csv_test.py
tests/jsoncollection2csv_test.py
tests/main_test.py
tests/singlejson2csv_test.py
tests/split_test.py
tweet_manager/__init__.py
tweet_manager/main.py
tweet_manager/data/__init__.py
tweet_manager/data/filters/__init__.py
tweet_manager/data/filters/filters.py
tweet_manager/lib/__init__.py
tweet_manager/lib/error_handling.py
tweet_manager/lib/filesystem.py
tweet_manager/lib/format_csv.py
tweet_manager/lib/json2csv.py
tweet_manager/lib/msg_printer.py
tweet_manager/tests/__init__.py
tweet_manager/tests/flat_test.py
tweet_manager/tests/json2csv_test.py
tweet_manager/tests/jsoncollection2csv_test.py
tweet_manager/tests/main_test.py
tweet_manager/tests/singlejson2csv_test.py
tweet_manager/tests/split_test.py
tweetmanager_serpucga-1.1.10.dist-info/LICENSE
tweetmanager_serpucga-1.1.10.dist-info/METADATA
tweetmanager_serpucga-1.1.10.dist-info/WHEEL
tweetmanager_serpucga-1.1.10.dist-info/top_level.txt
tweetmanager_serpucga-1.1.10.dist-info/RECORD
