Metadata-Version: 2.1
Name: tweetmanager-serpucga
Version: 1.1.10
Summary: A package for managing tweets
Home-page: https://gitlab.com/Serbaf/tweet-manager.git
Author: Sergio Puche García
Author-email: serpucga@protonmail.com
License: UNKNOWN
Platform: UNKNOWN
Classifier: Programming Language :: Python :: 3
Classifier: License :: OSI Approved :: MIT License
Classifier: Operating System :: OS Independent
Requires-Python: >=3.6
